botdependencies/__init__.py
botdependencies/baseline.py
botdependencies-1.0.dist-info/METADATA
botdependencies-1.0.dist-info/WHEEL
botdependencies-1.0.dist-info/top_level.txt
botdependencies-1.0.dist-info/RECORD
